MANIFEST.in
README.rst
setup.cfg
setup.py
django_easyoptions.egg-info/PKG-INFO
django_easyoptions.egg-info/SOURCES.txt
django_easyoptions.egg-info/dependency_links.txt
django_easyoptions.egg-info/not-zip-safe
django_easyoptions.egg-info/requires.txt
django_easyoptions.egg-info/top_level.txt
easyoptions/__init__.py
easyoptions/models.py
easyoptions/options.py
easyoptions/tests/__init__.py
easyoptions/tests/test_forms.py
easyoptions/tests/test_modelforms.py
easyoptions/tests/test_simple.py