Metadata-Version: 1.1
Name: django-easyoptions
Version: 0.1.0
Summary: Easily create extra Meta option classes on forms
Home-page: https://bitbucket.org/tim_heap/django-easyoptions
Author: Tim Heap
Author-email: tim@timheap.me
License: UNKNOWN
Platform: UNKNOWN
Classifier: Environment :: Web Environment
Classifier: Intended Audience :: Developers
Classifier: Operating System :: OS Independent
Classifier: Programming Language :: Python
Classifier: Framework :: Django
